MANIFEST.in
README.md
setup.cfg
setup.py
csg/__init__.py
csg/core.py
csg/geom.py
pycsg.egg-info/PKG-INFO
pycsg.egg-info/SOURCES.txt
pycsg.egg-info/dependency_links.txt
pycsg.egg-info/top_level.txt
test/__init__.py
test/test_bsp.py
test/test_csg.py
test/test_refine.py