Metadata-Version: 1.1
Name: pycsg
Version: 0.3.3
Summary: Constructive Solid Geometry (CSG)
Home-page: https://github.com/timknip/pycsg
Author: Tim Knip
Author-email: tim@floorplanner.com
License: MIT
Keywords: constructive solid geometry csg utilities
Platform: UNKNOWN
Classifier: Development Status :: 4 - Beta
Classifier: Topic :: Utilities
Classifier: License :: OSI Approved :: MIT License
